pyrag/__init__.py
pyrag/chat/__init__.py
pyrag/chat/chain.py
pyrag/chat/chat.py
pyrag/chat/db_message_history.py
pyrag/chat/knowledge.py
pyrag/chat/manager.py
pyrag/chat/model.py
pyrag/chat/session.py
pyrag/db/__init__.py
pyrag/db/database.py
pyrag/embeddings/__init__.py
pyrag/embeddings/base.py
pyrag/embeddings/embeddings.py
pyrag/embeddings/typing.py
pyrag/files/__init__.py
pyrag/files/file.py
pyrag/files/manager.py
pyrag/files/source/__init__.py
pyrag/files/source/base.py
pyrag/files/source/s3.py
pyrag/files/source/url.py
pyrag/helpers/__init__.py
pyrag/helpers/text.py
pyrag/search/__init__.py
pyrag/search/base.py
pyrag/search/typing.py
pyrag/search/vector.py
PyRAG-0.0.4.dist-info/LICENSE
PyRAG-0.0.4.dist-info/METADATA
PyRAG-0.0.4.dist-info/WHEEL
PyRAG-0.0.4.dist-info/top_level.txt
PyRAG-0.0.4.dist-info/RECORD
